abuse_finder/__init__.py
abuse_finder/domain.py
abuse_finder/email.py
abuse_finder/ip.py
abuse_finder/url.py
abuse_finder-0.2.dist-info/DESCRIPTION.rst
abuse_finder-0.2.dist-info/METADATA
abuse_finder-0.2.dist-info/RECORD
abuse_finder-0.2.dist-info/WHEEL
abuse_finder-0.2.dist-info/metadata.json
abuse_finder-0.2.dist-info/top_level.txt
